face_alignment/__init__.py
face_alignment/api.py
face_alignment/folder_data.py
face_alignment/utils.py
face_alignment/detection/__init__.py
face_alignment/detection/core.py
face_alignment/detection/blazeface/__init__.py
face_alignment/detection/blazeface/blazeface_detector.py
face_alignment/detection/blazeface/detect.py
face_alignment/detection/blazeface/net_blazeface.py
face_alignment/detection/blazeface/utils.py
face_alignment/detection/dlib/__init__.py
face_alignment/detection/dlib/dlib_detector.py
face_alignment/detection/folder/__init__.py
face_alignment/detection/folder/folder_detector.py
face_alignment/detection/sfd/__init__.py
face_alignment/detection/sfd/bbox.py
face_alignment/detection/sfd/detect.py
face_alignment/detection/sfd/net_s3fd.py
face_alignment/detection/sfd/sfd_detector.py
face_alignment-1.4.1.dist-info/LICENSE
face_alignment-1.4.1.dist-info/METADATA
face_alignment-1.4.1.dist-info/WHEEL
face_alignment-1.4.1.dist-info/top_level.txt
face_alignment-1.4.1.dist-info/zip-safe
face_alignment-1.4.1.dist-info/RECORD
