Metadata-Version: 2.1
Name: face-alignment
Version: 1.4.1
Summary: Detector 2D or 3D face landmarks from Python
Home-page: https://github.com/1adrianb/face-alignment
Author: Adrian Bulat
Author-email: adrian@adrianbulat.com
License: BSD
Classifier: Development Status :: 5 - Production/Stable
Classifier: Operating System :: OS Independent
Classifier: License :: OSI Approved :: BSD License
Classifier: Natural Language :: English
Classifier: Programming Language :: Python :: 3
Classifier: Programming Language :: Python :: 3.7
Classifier: Programming Language :: Python :: 3.8
Classifier: Programming Language :: Python :: 3.9
Classifier: Programming Language :: Python :: 3.10
Requires-Python: >=3
License-File: LICENSE
